apple_health_exporter/__init__.py
apple_health_exporter/__main__.py
apple_health_exporter-1.2.0.dist-info/LICENSE
apple_health_exporter-1.2.0.dist-info/WHEEL
apple_health_exporter-1.2.0.dist-info/entry_points.txt
apple_health_exporter-1.2.0.dist-info/METADATA
apple_health_exporter-1.2.0.dist-info/RECORD
