Metadata-Version: 2.1
Name: apple-health-exporter
Version: 1.2.0
Summary: Python module to export Apple Health dump file to a data frame for analysis
Home-page: https://github.com/mganjoo/apple-health-exporter
License: MIT
Author: Milind Ganjoo
Author-email: milind.ganjoo@gmail.com
Requires-Python: >=3.8,<4.0
Classifier: License :: OSI Approved :: MIT License
Classifier: Programming Language :: Python :: 3
Classifier: Programming Language :: Python :: 3.8
Classifier: Programming Language :: Python :: 3.9
Classifier: Programming Language :: Python :: 3.10
Classifier: Programming Language :: Python :: 3.11
Requires-Dist: lxml (>=4.9.2,<5.0.0)
Requires-Dist: pandas (>=1.5.2,<2.0.0)
Requires-Dist: pyarrow (>=10.0.1,<11.0.0)
Project-URL: Repository, https://github.com/mganjoo/apple-health-exporter
